hermetrics/__init__.py
hermetrics/damerau_levenshtein.py
hermetrics/dice.py
hermetrics/hamming.py
hermetrics/jaccard.py
hermetrics/jaro.py
hermetrics/jaro_winkler.py
hermetrics/levenshtein.py
hermetrics/metric.py
hermetrics/metric_comparator.py
hermetrics/osa.py
hermetrics/version.py
hermetrics/tests/__init__.py
hermetrics/tests/test_damerau_levenshtein.py
hermetrics/tests/test_dice.py
hermetrics/tests/test_hamming.py
hermetrics/tests/test_jaccard.py
hermetrics/tests/test_jaro.py
hermetrics/tests/test_jaro_winkler.py
hermetrics/tests/test_levenshtein.py
hermetrics/tests/test_metric.py
hermetrics/tests/test_metric_comparator.py
hermetrics/tests/test_osa.py
hermetrics-0.1.13.dist-info/LICENSE
hermetrics-0.1.13.dist-info/METADATA
hermetrics-0.1.13.dist-info/WHEEL
hermetrics-0.1.13.dist-info/top_level.txt
hermetrics-0.1.13.dist-info/RECORD
