Metadata-Version: 2.1
Name: hermetrics
Version: 0.1.13
Summary: A package for string distance and similarity metrics
Home-page: https://github.com/kampamocha/hermetrics
Author: kampamocha
Author-email: diego.campos.sobrino@gmail.com
License: MIT License
Keywords: string metric distance similarity
Platform: UNKNOWN
Classifier: Programming Language :: Python :: 3
Classifier: License :: OSI Approved :: MIT License
Classifier: Operating System :: OS Independent
Requires-Python: >=3.0
